sudoku.py
Trivial_Sudoku-2.0.dist-info/DESCRIPTION.rst
Trivial_Sudoku-2.0.dist-info/METADATA
Trivial_Sudoku-2.0.dist-info/RECORD
Trivial_Sudoku-2.0.dist-info/WHEEL
Trivial_Sudoku-2.0.dist-info/metadata.json
Trivial_Sudoku-2.0.dist-info/top_level.txt
