Metadata-Version: 2.0
Name: Trivial-Sudoku
Version: 2.0
Summary: A trvial Python implementation of a Sudoku solver
Home-page: https://github.com/alexpirine/python-trivial-sudoku
Author: Alexandre Syenchuk
Author-email: as@netica.fr
License: New BSD License
Platform: UNKNOWN
Classifier: Development Status :: 5 - Production/Stable
Classifier: Environment :: Console
Classifier: Environment :: Other Environment
Classifier: Intended Audience :: Developers
Classifier: Intended Audience :: Education
Classifier: Intended Audience :: Science/Research
Classifier: License :: OSI Approved :: BSD License
Classifier: Programming Language :: Python :: 2
Classifier: Programming Language :: Python :: 2.7
Classifier: Topic :: Education
Classifier: Topic :: Games/Entertainment :: Puzzle Games
Classifier: Topic :: Software Development :: Libraries :: Python Modules
